martapy/__init__.py
martapy/bus.py
martapy/rail.py
martapy-1.1.dist-info/DESCRIPTION.rst
martapy-1.1.dist-info/METADATA
martapy-1.1.dist-info/RECORD
martapy-1.1.dist-info/WHEEL
martapy-1.1.dist-info/metadata.json
martapy-1.1.dist-info/top_level.txt
