Metadata-Version: 2.0
Name: martapy
Version: 1.1
Summary: Wrapper for MARTA realtime rail/bus APIs
Home-page: https://github.com/arcward/fbparser
Author: Edward Wells
Author-email: git@edward.sh
License: MIT
Keywords: MARTA API rail train Atlanta Georgia GA ATL itsmarta
Platform: UNKNOWN
Requires-Dist: requests
